drop_email/__init__.py
drop_email/cli.py
drop_email/config.py
drop_email/config.yaml.example
drop_email/email_sender.py
drop_email/html_generator.py
drop_email-0.1.3.dist-info/licenses/LICENSE
drop_email-0.1.3.dist-info/METADATA
drop_email-0.1.3.dist-info/WHEEL
drop_email-0.1.3.dist-info/entry_points.txt
drop_email-0.1.3.dist-info/top_level.txt
drop_email-0.1.3.dist-info/RECORD
